<?xml version="1.0" encoding="UTF-8" standalone="yes"?>
<DatabaseModel VersionId="2.3">
    <Name>Multilens</Name>
    <Description></Description>
    <DatabaseEngine>
        <Name>sqlite</Name>
        <Version>3.x</Version>
    </DatabaseEngine>
    <Counters>
        <Counter>
            <Name>table</Name>
            <Value>9</Value>
            <Prefix>t</Prefix>
        </Counter>
        <Counter>
            <Name>column</Name>
            <Value>83</Value>
            <Prefix>c</Prefix>
        </Counter>
        <Counter>
            <Name>index</Name>
            <Value>0</Value>
            <Prefix>i</Prefix>
        </Counter>
        <Counter>
            <Name>reference</Name>
            <Value>18</Value>
            <Prefix>r</Prefix>
        </Counter>
        <Counter>
            <Name>table_check</Name>
            <Value>1</Value>
            <Prefix>tc</Prefix>
        </Counter>
        <Counter>
            <Name>alternate_key</Name>
            <Value>2</Value>
            <Prefix>a</Prefix>
        </Counter>
        <Counter>
            <Name>sequence</Name>
            <Value>0</Value>
            <Prefix>s</Prefix>
        </Counter>
        <Counter>
            <Name>note</Name>
            <Value>0</Value>
            <Prefix>n</Prefix>
        </Counter>
        <Counter>
            <Name>view</Name>
            <Value>2</Value>
            <Prefix>v</Prefix>
        </Counter>
        <Counter>
            <Name>view_column</Name>
            <Value>0</Value>
            <Prefix>vc</Prefix>
        </Counter>
        <Counter>
            <Name>area</Name>
            <Value>0</Value>
            <Prefix>ar</Prefix>
        </Counter>
        <Counter>
            <Name>text</Name>
            <Value>0</Value>
            <Prefix>tx</Prefix>
        </Counter>
        <Counter>
            <Name>tableDisplay</Name>
            <Value>10</Value>
            <Prefix>td</Prefix>
        </Counter>
        <Counter>
            <Name>viewDisplay</Name>
            <Value>2</Value>
            <Prefix>vd</Prefix>
        </Counter>
        <Counter>
            <Name>referenceDisplay</Name>
            <Value>18</Value>
            <Prefix>rd</Prefix>
        </Counter>
    </Counters>
    <AdditionalSQLBeforeCreate></AdditionalSQLBeforeCreate>
    <AdditionalSQLAfterCreate></AdditionalSQLAfterCreate>
    <AdditionalSQLBeforeDrop></AdditionalSQLBeforeDrop>
    <AdditionalSQLAfterDrop></AdditionalSQLAfterDrop>
    <Tables>
        <Table Id="t1">
            <Name>employees</Name>
            <Description></Description>
            <Columns>
                <Column Id="c1">
                    <Name>id</Name>
                    <Type>integer</Type>
                    <Description></Description>
                    <Nullable>false</Nullable>
                    <DefaultValue></DefaultValue>
                    <CheckExpression></CheckExpression>
                    <Properties>
                        <Property>
                            <Name>autoincrement</Name>
                            <Value>true</Value>
                        </Property>
                    </Properties>
                </Column>
                <Column Id="c2">
                    <Name>user</Name>
                    <Type>varchar(255)</Type>
                    <Description></Description>
                    <Nullable>false</Nullable>
                    <DefaultValue></DefaultValue>
                    <CheckExpression></CheckExpression>
                    <Properties/>
                </Column>
                <Column Id="c3">
                    <Name>password</Name>
                    <Type>varchar(255)</Type>
                    <Description></Description>
                    <Nullable>false</Nullable>
                    <DefaultValue></DefaultValue>
                    <CheckExpression></CheckExpression>
                    <Properties/>
                </Column>
                <Column Id="c4">
                    <Name>email</Name>
                    <Type>varchar(255)</Type>
                    <Description></Description>
                    <Nullable>false</Nullable>
                    <DefaultValue></DefaultValue>
                    <CheckExpression></CheckExpression>
                    <Properties/>
                </Column>
                <Column Id="c5">
                    <Name>name</Name>
                    <Type>varchar(255)</Type>
                    <Description></Description>
                    <Nullable>false</Nullable>
                    <DefaultValue></DefaultValue>
                    <CheckExpression></CheckExpression>
                    <Properties/>
                </Column>
                <Column Id="c6">
                    <Name>cpf</Name>
                    <Type>varchar(255)</Type>
                    <Description></Description>
                    <Nullable>false</Nullable>
                    <DefaultValue></DefaultValue>
                    <CheckExpression></CheckExpression>
                    <Properties/>
                </Column>
                <Column Id="c7">
                    <Name>admin</Name>
                    <Type>boolean</Type>
                    <Description></Description>
                    <Nullable>false</Nullable>
                    <DefaultValue>False</DefaultValue>
                    <CheckExpression></CheckExpression>
                    <Properties/>
                </Column>
            </Columns>
            <PrimaryKey>
                <Name></Name>
                <Columns>
                    <Column>c1</Column>
                </Columns>
            </PrimaryKey>
            <AlternateKeys/>
            <Indexes/>
            <TableChecks/>
            <AdditionalSQLBefore></AdditionalSQLBefore>
            <AdditionalSQLAfter></AdditionalSQLAfter>
            <Properties/>
        </Table>
        <Table Id="t2">
            <Name>storage</Name>
            <Description></Description>
            <Columns>
                <Column Id="c8">
                    <Name>id</Name>
                    <Type>integer</Type>
                    <Description></Description>
                    <Nullable>false</Nullable>
                    <DefaultValue></DefaultValue>
                    <CheckExpression></CheckExpression>
                    <Properties>
                        <Property>
                            <Name>autoincrement</Name>
                            <Value>true</Value>
                        </Property>
                    </Properties>
                </Column>
                <Column Id="c9">
                    <Name>name</Name>
                    <Type>varchar(255)</Type>
                    <Description></Description>
                    <Nullable>false</Nullable>
                    <DefaultValue></DefaultValue>
                    <CheckExpression></CheckExpression>
                    <Properties/>
                </Column>
                <Column Id="c10">
                    <Name>price</Name>
                    <Type>decimal(10,2)</Type>
                    <Description></Description>
                    <Nullable>false</Nullable>
                    <DefaultValue></DefaultValue>
                    <CheckExpression></CheckExpression>
                    <Properties/>
                </Column>
                <Column Id="c11">
                    <Name>unity</Name>
                    <Type>varchar(10)</Type>
                    <Description></Description>
                    <Nullable>false</Nullable>
                    <DefaultValue></DefaultValue>
                    <CheckExpression></CheckExpression>
                    <Properties/>
                </Column>
                <Column Id="c12">
                    <Name>avaliable</Name>
                    <Type>boolean</Type>
                    <Description></Description>
                    <Nullable>false</Nullable>
                    <DefaultValue></DefaultValue>
                    <CheckExpression></CheckExpression>
                    <Properties/>
                </Column>
            </Columns>
            <PrimaryKey>
                <Name></Name>
                <Columns>
                    <Column>c8</Column>
                </Columns>
            </PrimaryKey>
            <AlternateKeys/>
            <Indexes/>
            <TableChecks/>
            <AdditionalSQLBefore></AdditionalSQLBefore>
            <AdditionalSQLAfter></AdditionalSQLAfter>
            <Properties/>
        </Table>
        <Table Id="t3">
            <Name>balance</Name>
            <Description></Description>
            <Columns>
                <Column Id="c77">
                    <Name>id</Name>
                    <Type>integer</Type>
                    <Description></Description>
                    <Nullable>false</Nullable>
                    <DefaultValue></DefaultValue>
                    <CheckExpression></CheckExpression>
                    <Properties/>
                </Column>
                <Column Id="c16">
                    <Name>item_id</Name>
                    <Type>integer</Type>
                    <Description></Description>
                    <Nullable>false</Nullable>
                    <DefaultValue></DefaultValue>
                    <CheckExpression></CheckExpression>
                    <Properties/>
                </Column>
                <Column Id="c18">
                    <Name>quant</Name>
                    <Type>integer</Type>
                    <Description></Description>
                    <Nullable>false</Nullable>
                    <DefaultValue></DefaultValue>
                    <CheckExpression></CheckExpression>
                    <Properties/>
                </Column>
                <Column Id="c19">
                    <Name>date</Name>
                    <Type>date</Type>
                    <Description></Description>
                    <Nullable>false</Nullable>
                    <DefaultValue></DefaultValue>
                    <CheckExpression></CheckExpression>
                    <Properties/>
                </Column>
                <Column Id="c20">
                    <Name>event</Name>
                    <Type>varchar(255)</Type>
                    <Description></Description>
                    <Nullable>false</Nullable>
                    <DefaultValue></DefaultValue>
                    <CheckExpression></CheckExpression>
                    <Properties/>
                </Column>
            </Columns>
            <PrimaryKey>
                <Name></Name>
                <Columns>
                    <Column>c77</Column>
                </Columns>
            </PrimaryKey>
            <AlternateKeys/>
            <Indexes/>
            <TableChecks/>
            <AdditionalSQLBefore></AdditionalSQLBefore>
            <AdditionalSQLAfter></AdditionalSQLAfter>
            <Properties/>
        </Table>
        <Table Id="t4">
            <Name>order</Name>
            <Description></Description>
            <Columns>
                <Column Id="c21">
                    <Name>id</Name>
                    <Type>integer</Type>
                    <Description></Description>
                    <Nullable>false</Nullable>
                    <DefaultValue></DefaultValue>
                    <CheckExpression></CheckExpression>
                    <Properties>
                        <Property>
                            <Name>collate</Name>
                            <Value>BINARY</Value>
                        </Property>
                    </Properties>
                </Column>
                <Column Id="c26">
                    <Name>employee_id</Name>
                    <Type>integer</Type>
                    <Description></Description>
                    <Nullable>false</Nullable>
                    <DefaultValue></DefaultValue>
                    <CheckExpression></CheckExpression>
                    <Properties/>
                </Column>
                <Column Id="c58">
                    <Name>register_id</Name>
                    <Type>integer</Type>
                    <Description></Description>
                    <Nullable>false</Nullable>
                    <DefaultValue></DefaultValue>
                    <CheckExpression></CheckExpression>
                    <Properties/>
                </Column>
                <Column Id="c23">
                    <Name>date</Name>
                    <Type>date</Type>
                    <Description></Description>
                    <Nullable>false</Nullable>
                    <DefaultValue></DefaultValue>
                    <CheckExpression></CheckExpression>
                    <Properties/>
                </Column>
                <Column Id="c24">
                    <Name>type_pgto</Name>
                    <Type>varchar(10)</Type>
                    <Description></Description>
                    <Nullable>false</Nullable>
                    <DefaultValue></DefaultValue>
                    <CheckExpression></CheckExpression>
                    <Properties/>
                </Column>
                <Column Id="c25">
                    <Name>type</Name>
                    <Type>varchar(10)</Type>
                    <Description></Description>
                    <Nullable>false</Nullable>
                    <DefaultValue></DefaultValue>
                    <CheckExpression></CheckExpression>
                    <Properties/>
                </Column>
            </Columns>
            <PrimaryKey>
                <Name></Name>
                <Columns>
                    <Column>c21</Column>
                </Columns>
            </PrimaryKey>
            <AlternateKeys/>
            <Indexes/>
            <TableChecks/>
            <AdditionalSQLBefore></AdditionalSQLBefore>
            <AdditionalSQLAfter></AdditionalSQLAfter>
            <Properties/>
        </Table>
        <Table Id="t5">
            <Name>desc_order</Name>
            <Description></Description>
            <Columns>
                <Column Id="c83">
                    <Name>id</Name>
                    <Type>integer</Type>
                    <Description></Description>
                    <Nullable>false</Nullable>
                    <DefaultValue></DefaultValue>
                    <CheckExpression></CheckExpression>
                    <Properties/>
                </Column>
                <Column Id="c27">
                    <Name>order_id</Name>
                    <Type>integer</Type>
                    <Description></Description>
                    <Nullable>false</Nullable>
                    <DefaultValue></DefaultValue>
                    <CheckExpression></CheckExpression>
                    <Properties/>
                </Column>
                <Column Id="c28">
                    <Name>product_id</Name>
                    <Type>integer</Type>
                    <Description></Description>
                    <Nullable>false</Nullable>
                    <DefaultValue></DefaultValue>
                    <CheckExpression></CheckExpression>
                    <Properties/>
                </Column>
                <Column Id="c29">
                    <Name>quant</Name>
                    <Type>integer</Type>
                    <Description></Description>
                    <Nullable>false</Nullable>
                    <DefaultValue></DefaultValue>
                    <CheckExpression></CheckExpression>
                    <Properties/>
                </Column>
                <Column Id="c30">
                    <Name>unity_value</Name>
                    <Type>integer</Type>
                    <Description></Description>
                    <Nullable>false</Nullable>
                    <DefaultValue></DefaultValue>
                    <CheckExpression></CheckExpression>
                    <Properties/>
                </Column>
                <Column Id="c79">
                    <Name>discount</Name>
                    <Type>decimal(2,2)</Type>
                    <Description></Description>
                    <Nullable>false</Nullable>
                    <DefaultValue></DefaultValue>
                    <CheckExpression></CheckExpression>
                    <Properties/>
                </Column>
            </Columns>
            <PrimaryKey>
                <Name></Name>
                <Columns>
                    <Column>c83</Column>
                </Columns>
            </PrimaryKey>
            <AlternateKeys/>
            <Indexes/>
            <TableChecks/>
            <AdditionalSQLBefore></AdditionalSQLBefore>
            <AdditionalSQLAfter></AdditionalSQLAfter>
            <Properties/>
        </Table>
        <Table Id="t7">
            <Name>register</Name>
            <Description></Description>
            <Columns>
                <Column Id="c40">
                    <Name>id</Name>
                    <Type>integer</Type>
                    <Description></Description>
                    <Nullable>false</Nullable>
                    <DefaultValue></DefaultValue>
                    <CheckExpression></CheckExpression>
                    <Properties/>
                </Column>
                <Column Id="c41">
                    <Name>client_id</Name>
                    <Type>integer</Type>
                    <Description></Description>
                    <Nullable>false</Nullable>
                    <DefaultValue></DefaultValue>
                    <CheckExpression></CheckExpression>
                    <Properties/>
                </Column>
                <Column Id="c74">
                    <Name>institution_id</Name>
                    <Type>integer</Type>
                    <Description></Description>
                    <Nullable>false</Nullable>
                    <DefaultValue></DefaultValue>
                    <CheckExpression></CheckExpression>
                    <Properties/>
                </Column>
                <Column Id="c42">
                    <Name>zip</Name>
                    <Type>integer</Type>
                    <Description></Description>
                    <Nullable>false</Nullable>
                    <DefaultValue></DefaultValue>
                    <CheckExpression></CheckExpression>
                    <Properties/>
                </Column>
                <Column Id="c43">
                    <Name>country</Name>
                    <Type>varchar(255)</Type>
                    <Description></Description>
                    <Nullable>false</Nullable>
                    <DefaultValue></DefaultValue>
                    <CheckExpression></CheckExpression>
                    <Properties/>
                </Column>
                <Column Id="c75">
                    <Name>address</Name>
                    <Type>varchar(255)</Type>
                    <Description></Description>
                    <Nullable>false</Nullable>
                    <DefaultValue></DefaultValue>
                    <CheckExpression></CheckExpression>
                    <Properties/>
                </Column>
                <Column Id="c76">
                    <Name>type</Name>
                    <Type>varchar(255)</Type>
                    <Description></Description>
                    <Nullable>false</Nullable>
                    <DefaultValue></DefaultValue>
                    <CheckExpression></CheckExpression>
                    <Properties/>
                </Column>
            </Columns>
            <PrimaryKey>
                <Name></Name>
                <Columns>
                    <Column>c40</Column>
                </Columns>
            </PrimaryKey>
            <AlternateKeys/>
            <Indexes/>
            <TableChecks/>
            <AdditionalSQLBefore></AdditionalSQLBefore>
            <AdditionalSQLAfter></AdditionalSQLAfter>
            <Properties/>
        </Table>
        <Table Id="t8">
            <Name>doctor</Name>
            <Description></Description>
            <Columns>
                <Column Id="c45">
                    <Name>register_id</Name>
                    <Type>integer</Type>
                    <Description></Description>
                    <Nullable>false</Nullable>
                    <DefaultValue></DefaultValue>
                    <CheckExpression></CheckExpression>
                    <Properties/>
                </Column>
                <Column Id="c81">
                    <Name>id</Name>
                    <Type>integer</Type>
                    <Description></Description>
                    <Nullable>false</Nullable>
                    <DefaultValue></DefaultValue>
                    <CheckExpression></CheckExpression>
                    <Properties/>
                </Column>
                <Column Id="c49">
                    <Name>name</Name>
                    <Type>varchar(255)</Type>
                    <Description></Description>
                    <Nullable>false</Nullable>
                    <DefaultValue></DefaultValue>
                    <CheckExpression></CheckExpression>
                    <Properties/>
                </Column>
                <Column Id="c82">
                    <Name>sex</Name>
                    <Type>varchar(1)</Type>
                    <Description></Description>
                    <Nullable>false</Nullable>
                    <DefaultValue></DefaultValue>
                    <CheckExpression></CheckExpression>
                    <Properties/>
                </Column>
                <Column Id="c50">
                    <Name>cpf</Name>
                    <Type>integer</Type>
                    <Description></Description>
                    <Nullable>false</Nullable>
                    <DefaultValue></DefaultValue>
                    <CheckExpression></CheckExpression>
                    <Properties/>
                </Column>
                <Column Id="c53">
                    <Name>rg</Name>
                    <Type>integer</Type>
                    <Description></Description>
                    <Nullable>false</Nullable>
                    <DefaultValue></DefaultValue>
                    <CheckExpression></CheckExpression>
                    <Properties/>
                </Column>
                <Column Id="c54">
                    <Name>crm</Name>
                    <Type>integer</Type>
                    <Description></Description>
                    <Nullable>false</Nullable>
                    <DefaultValue></DefaultValue>
                    <CheckExpression></CheckExpression>
                    <Properties/>
                </Column>
                <Column Id="c51">
                    <Name>cel</Name>
                    <Type>integer</Type>
                    <Description></Description>
                    <Nullable>false</Nullable>
                    <DefaultValue></DefaultValue>
                    <CheckExpression></CheckExpression>
                    <Properties/>
                </Column>
                <Column Id="c52">
                    <Name>phone</Name>
                    <Type>integer</Type>
                    <Description></Description>
                    <Nullable>false</Nullable>
                    <DefaultValue></DefaultValue>
                    <CheckExpression></CheckExpression>
                    <Properties/>
                </Column>
                <Column Id="c55">
                    <Name>email</Name>
                    <Type>varchar(255)</Type>
                    <Description></Description>
                    <Nullable>false</Nullable>
                    <DefaultValue></DefaultValue>
                    <CheckExpression></CheckExpression>
                    <Properties/>
                </Column>
            </Columns>
            <PrimaryKey>
                <Name></Name>
                <Columns>
                    <Column>c81</Column>
                </Columns>
            </PrimaryKey>
            <AlternateKeys/>
            <Indexes/>
            <TableChecks/>
            <AdditionalSQLBefore></AdditionalSQLBefore>
            <AdditionalSQLAfter></AdditionalSQLAfter>
            <Properties/>
        </Table>
        <Table Id="t9">
            <Name>institution</Name>
            <Description></Description>
            <Columns>
                <Column Id="c80">
                    <Name>id</Name>
                    <Type>integer</Type>
                    <Description></Description>
                    <Nullable>false</Nullable>
                    <DefaultValue></DefaultValue>
                    <CheckExpression></CheckExpression>
                    <Properties/>
                </Column>
                <Column Id="c59">
                    <Name>register_id</Name>
                    <Type>integer</Type>
                    <Description></Description>
                    <Nullable>false</Nullable>
                    <DefaultValue></DefaultValue>
                    <CheckExpression></CheckExpression>
                    <Properties/>
                </Column>
                <Column Id="c60">
                    <Name>name</Name>
                    <Type>varchar(100)</Type>
                    <Description></Description>
                    <Nullable>false</Nullable>
                    <DefaultValue></DefaultValue>
                    <CheckExpression></CheckExpression>
                    <Properties/>
                </Column>
                <Column Id="c61">
                    <Name>cnpj</Name>
                    <Type>integer</Type>
                    <Description></Description>
                    <Nullable>false</Nullable>
                    <DefaultValue></DefaultValue>
                    <CheckExpression></CheckExpression>
                    <Properties/>
                </Column>
                <Column Id="c62">
                    <Name>adm_name</Name>
                    <Type>varchar(100)</Type>
                    <Description></Description>
                    <Nullable>false</Nullable>
                    <DefaultValue></DefaultValue>
                    <CheckExpression></CheckExpression>
                    <Properties/>
                </Column>
                <Column Id="c68">
                    <Name>adm_email</Name>
                    <Type>varchar(50)</Type>
                    <Description></Description>
                    <Nullable>false</Nullable>
                    <DefaultValue></DefaultValue>
                    <CheckExpression></CheckExpression>
                    <Properties/>
                </Column>
                <Column Id="c63">
                    <Name>adm_cel</Name>
                    <Type>integer</Type>
                    <Description></Description>
                    <Nullable>false</Nullable>
                    <DefaultValue></DefaultValue>
                    <CheckExpression></CheckExpression>
                    <Properties/>
                </Column>
                <Column Id="c64">
                    <Name>adm_phone</Name>
                    <Type>integer</Type>
                    <Description></Description>
                    <Nullable>false</Nullable>
                    <DefaultValue></DefaultValue>
                    <CheckExpression></CheckExpression>
                    <Properties/>
                </Column>
                <Column Id="c65">
                    <Name>enf_name</Name>
                    <Type>varchar(100)</Type>
                    <Description></Description>
                    <Nullable>false</Nullable>
                    <DefaultValue></DefaultValue>
                    <CheckExpression></CheckExpression>
                    <Properties/>
                </Column>
                <Column Id="c69">
                    <Name>enf_email</Name>
                    <Type>varchar(50)</Type>
                    <Description></Description>
                    <Nullable>false</Nullable>
                    <DefaultValue></DefaultValue>
                    <CheckExpression></CheckExpression>
                    <Properties/>
                </Column>
                <Column Id="c66">
                    <Name>enf_cel</Name>
                    <Type>integer</Type>
                    <Description></Description>
                    <Nullable>false</Nullable>
                    <DefaultValue></DefaultValue>
                    <CheckExpression></CheckExpression>
                    <Properties/>
                </Column>
                <Column Id="c67">
                    <Name>enf_phone</Name>
                    <Type>integer</Type>
                    <Description></Description>
                    <Nullable>false</Nullable>
                    <DefaultValue></DefaultValue>
                    <CheckExpression></CheckExpression>
                    <Properties/>
                </Column>
            </Columns>
            <PrimaryKey>
                <Name></Name>
                <Columns>
                    <Column>c80</Column>
                </Columns>
            </PrimaryKey>
            <AlternateKeys/>
            <Indexes/>
            <TableChecks/>
            <AdditionalSQLBefore></AdditionalSQLBefore>
            <AdditionalSQLAfter></AdditionalSQLAfter>
            <Properties/>
        </Table>
    </Tables>
    <Views/>
    <References>
        <Reference Id="r3">
            <Name>storage_items</Name>
            <Description></Description>
            <PKTable>t2</PKTable>
            <FKTable>t3</FKTable>
            <PKRole></PKRole>
            <FKRole></FKRole>
            <ReferenceColumns>
                <ReferenceColumn>
                    <PKColumn>c8</PKColumn>
                    <FKColumn>c16</FKColumn>
                </ReferenceColumn>
            </ReferenceColumns>
            <Cardinality>1..*</Cardinality>
            <Mandatory>true</Mandatory>
            <OnUpdateAction>None</OnUpdateAction>
            <OnDeleteAction>None</OnDeleteAction>
            <Properties/>
        </Reference>
        <Reference Id="r9">
            <Name>order_employees</Name>
            <Description></Description>
            <PKTable>t1</PKTable>
            <FKTable>t4</FKTable>
            <PKRole></PKRole>
            <FKRole></FKRole>
            <ReferenceColumns>
                <ReferenceColumn>
                    <PKColumn>c1</PKColumn>
                    <FKColumn>c26</FKColumn>
                </ReferenceColumn>
            </ReferenceColumns>
            <Cardinality>1..*</Cardinality>
            <Mandatory>true</Mandatory>
            <OnUpdateAction>None</OnUpdateAction>
            <OnDeleteAction>None</OnDeleteAction>
            <Properties/>
        </Reference>
        <Reference Id="r10">
            <Name>desc_order_order</Name>
            <Description></Description>
            <PKTable>t4</PKTable>
            <FKTable>t5</FKTable>
            <PKRole></PKRole>
            <FKRole></FKRole>
            <ReferenceColumns>
                <ReferenceColumn>
                    <PKColumn>c21</PKColumn>
                    <FKColumn>c27</FKColumn>
                </ReferenceColumn>
            </ReferenceColumns>
            <Cardinality>1..*</Cardinality>
            <Mandatory>false</Mandatory>
            <OnUpdateAction>None</OnUpdateAction>
            <OnDeleteAction>None</OnDeleteAction>
            <Properties/>
        </Reference>
        <Reference Id="r14">
            <Name>storage_desc_order</Name>
            <Description></Description>
            <PKTable>t2</PKTable>
            <FKTable>t5</FKTable>
            <PKRole></PKRole>
            <FKRole></FKRole>
            <ReferenceColumns>
                <ReferenceColumn>
                    <PKColumn>c8</PKColumn>
                    <FKColumn>c28</FKColumn>
                </ReferenceColumn>
            </ReferenceColumns>
            <Cardinality>1..*</Cardinality>
            <Mandatory>true</Mandatory>
            <OnUpdateAction>None</OnUpdateAction>
            <OnDeleteAction>None</OnDeleteAction>
            <Properties/>
        </Reference>
        <Reference Id="r15">
            <Name>address_client</Name>
            <Description></Description>
            <PKTable>t7</PKTable>
            <FKTable>t8</FKTable>
            <PKRole></PKRole>
            <FKRole></FKRole>
            <ReferenceColumns>
                <ReferenceColumn>
                    <PKColumn>c40</PKColumn>
                    <FKColumn>c45</FKColumn>
                </ReferenceColumn>
            </ReferenceColumns>
            <Cardinality>0..1</Cardinality>
            <Mandatory>true</Mandatory>
            <OnUpdateAction>None</OnUpdateAction>
            <OnDeleteAction>None</OnDeleteAction>
            <Properties/>
        </Reference>
        <Reference Id="r17">
            <Name>order_register</Name>
            <Description></Description>
            <PKTable>t7</PKTable>
            <FKTable>t4</FKTable>
            <PKRole></PKRole>
            <FKRole></FKRole>
            <ReferenceColumns>
                <ReferenceColumn>
                    <PKColumn>c40</PKColumn>
                    <FKColumn>c58</FKColumn>
                </ReferenceColumn>
            </ReferenceColumns>
            <Cardinality>1..*</Cardinality>
            <Mandatory>true</Mandatory>
            <OnUpdateAction>None</OnUpdateAction>
            <OnDeleteAction>None</OnDeleteAction>
            <Properties/>
        </Reference>
        <Reference Id="r18">
            <Name>register_institution</Name>
            <Description></Description>
            <PKTable>t7</PKTable>
            <FKTable>t9</FKTable>
            <PKRole></PKRole>
            <FKRole></FKRole>
            <ReferenceColumns>
                <ReferenceColumn>
                    <PKColumn>c40</PKColumn>
                    <FKColumn>c59</FKColumn>
                </ReferenceColumn>
            </ReferenceColumns>
            <Cardinality>1..1</Cardinality>
            <Mandatory>true</Mandatory>
            <OnUpdateAction>None</OnUpdateAction>
            <OnDeleteAction>None</OnDeleteAction>
            <Properties/>
        </Reference>
    </References>
    <Sequences/>
    <Notes/>
    <Areas/>
    <Texts/>
    <TableDisplays>
        <TableDisplay Id="td1">
            <X>6681.5</X>
            <Y>6746.5</Y>
            <Width>161.0</Width>
            <Height>130.0</Height>
            <LineColor>#000000</LineColor>
            <FillColor>#ffffff</FillColor>
            <Table>t1</Table>
            <FixedSize>false</FixedSize>
        </TableDisplay>
        <TableDisplay Id="td2">
            <X>6920.5</X>
            <Y>7124.5</Y>
            <Width>165.0</Width>
            <Height>102.0</Height>
            <LineColor>#000000</LineColor>
            <FillColor>#ffffff</FillColor>
            <Table>t2</Table>
            <FixedSize>false</FixedSize>
        </TableDisplay>
        <TableDisplay Id="td3">
            <X>6924.5</X>
            <Y>6979.5</Y>
            <Width>161.0</Width>
            <Height>102.0</Height>
            <LineColor>#000000</LineColor>
            <FillColor>#ffffff</FillColor>
            <Table>t3</Table>
            <FixedSize>false</FixedSize>
        </TableDisplay>
        <TableDisplay Id="td4">
            <X>6697.5</X>
            <Y>6949.5</Y>
            <Width>176.0</Width>
            <Height>130.0</Height>
            <LineColor>#000000</LineColor>
            <FillColor>#ffffff</FillColor>
            <Table>t4</Table>
            <FixedSize>false</FixedSize>
        </TableDisplay>
        <TableDisplay Id="td6">
            <X>6719.5</X>
            <Y>7124.5</Y>
            <Width>167.0</Width>
            <Height>116.0</Height>
            <LineColor>#000000</LineColor>
            <FillColor>#ffffff</FillColor>
            <Table>t5</Table>
            <FixedSize>false</FixedSize>
        </TableDisplay>
        <TableDisplay Id="td8">
            <X>6481.5</X>
            <Y>6950.5</Y>
            <Width>175.0</Width>
            <Height>130.0</Height>
            <LineColor>#000000</LineColor>
            <FillColor>#ffffff</FillColor>
            <Table>t7</Table>
            <FixedSize>false</FixedSize>
        </TableDisplay>
        <TableDisplay Id="td9">
            <X>6476.5</X>
            <Y>6743.5</Y>
            <Width>167.0</Width>
            <Height>174.0</Height>
            <LineColor>#000000</LineColor>
            <FillColor>#ffffff</FillColor>
            <Table>t8</Table>
            <FixedSize>false</FixedSize>
        </TableDisplay>
        <TableDisplay Id="td10">
            <X>6274.5</X>
            <Y>6746.5</Y>
            <Width>182.0</Width>
            <Height>202.0</Height>
            <LineColor>#000000</LineColor>
            <FillColor>#ffffff</FillColor>
            <Table>t9</Table>
            <FixedSize>false</FixedSize>
        </TableDisplay>
    </TableDisplays>
    <ViewDisplays/>
    <ReferenceDisplays>
        <ReferenceDisplay Id="rd3">
            <Color>#000000</Color>
            <Type>Vertical_4CP</Type>
            <ControlPoints>
                <ControlPoint>
                    <X>7018.5</X>
                    <Y>7134.5</Y>
                </ControlPoint>
                <ControlPoint>
                    <X>7018.5</X>
                    <Y>7037.5</Y>
                </ControlPoint>
                <ControlPoint>
                    <X>6956.5</X>
                    <Y>7037.5</Y>
                </ControlPoint>
                <ControlPoint>
                    <X>6956.5</X>
                    <Y>6989.5</Y>
                </ControlPoint>
            </ControlPoints>
            <PkTableDisplay>td2</PkTableDisplay>
            <FkTableDisplay>td3</FkTableDisplay>
            <Reference>r3</Reference>
        </ReferenceDisplay>
        <ReferenceDisplay Id="rd9">
            <Color>#000000</Color>
            <Type>Vertical_2CP</Type>
            <ControlPoints>
                <ControlPoint>
                    <X>6774.5</X>
                    <Y>6837.5</Y>
                </ControlPoint>
                <ControlPoint>
                    <X>6774.5</X>
                    <Y>6986.5</Y>
                </ControlPoint>
            </ControlPoints>
            <PkTableDisplay>td1</PkTableDisplay>
            <FkTableDisplay>td4</FkTableDisplay>
            <Reference>r9</Reference>
        </ReferenceDisplay>
        <ReferenceDisplay Id="rd10">
            <Color>#000000</Color>
            <Type>Vertical_2CP</Type>
            <ControlPoints>
                <ControlPoint>
                    <X>6776.5</X>
                    <Y>7048.5</Y>
                </ControlPoint>
                <ControlPoint>
                    <X>6776.5</X>
                    <Y>7178.5</Y>
                </ControlPoint>
            </ControlPoints>
            <PkTableDisplay>td4</PkTableDisplay>
            <FkTableDisplay>td6</FkTableDisplay>
            <Reference>r10</Reference>
        </ReferenceDisplay>
        <ReferenceDisplay Id="rd14">
            <Color>#000000</Color>
            <Type>Horizontal_2CP</Type>
            <ControlPoints>
                <ControlPoint>
                    <X>7039.5</X>
                    <Y>7181.5</Y>
                </ControlPoint>
                <ControlPoint>
                    <X>6802.5</X>
                    <Y>7181.5</Y>
                </ControlPoint>
            </ControlPoints>
            <PkTableDisplay>td2</PkTableDisplay>
            <FkTableDisplay>td6</FkTableDisplay>
            <Reference>r14</Reference>
        </ReferenceDisplay>
        <ReferenceDisplay Id="rd15">
            <Color>#000000</Color>
            <Type>Vertical_2CP</Type>
            <ControlPoints>
                <ControlPoint>
                    <X>6528.5</X>
                    <Y>6989.5</Y>
                </ControlPoint>
                <ControlPoint>
                    <X>6528.5</X>
                    <Y>6782.5</Y>
                </ControlPoint>
            </ControlPoints>
            <PkTableDisplay>td8</PkTableDisplay>
            <FkTableDisplay>td9</FkTableDisplay>
            <Reference>r15</Reference>
        </ReferenceDisplay>
        <ReferenceDisplay Id="rd17">
            <Color>#000000</Color>
            <Type>Horizontal_2CP</Type>
            <ControlPoints>
                <ControlPoint>
                    <X>6586.5</X>
                    <Y>7034.5</Y>
                </ControlPoint>
                <ControlPoint>
                    <X>6786.5</X>
                    <Y>7034.5</Y>
                </ControlPoint>
            </ControlPoints>
            <PkTableDisplay>td8</PkTableDisplay>
            <FkTableDisplay>td4</FkTableDisplay>
            <Reference>r17</Reference>
        </ReferenceDisplay>
        <ReferenceDisplay Id="rd18">
            <Color>#000000</Color>
            <Type>Horizontal_4CP</Type>
            <ControlPoints>
                <ControlPoint>
                    <X>6532.5</X>
                    <Y>7007.5</Y>
                </ControlPoint>
                <ControlPoint>
                    <X>6465.5</X>
                    <Y>7007.5</Y>
                </ControlPoint>
                <ControlPoint>
                    <X>6465.5</X>
                    <Y>6931.5</Y>
                </ControlPoint>
                <ControlPoint>
                    <X>6397.5</X>
                    <Y>6931.5</Y>
                </ControlPoint>
            </ControlPoints>
            <PkTableDisplay>td8</PkTableDisplay>
            <FkTableDisplay>td10</FkTableDisplay>
            <Reference>r18</Reference>
        </ReferenceDisplay>
    </ReferenceDisplays>
    <Properties>
        <Property>
            <Name>pdf-printer-paper-size</Name>
            <Value>A4</Value>
        </Property>
        <Property>
            <Name>pdf-printer-margin-top</Name>
            <Value>10</Value>
        </Property>
        <Property>
            <Name>pdf-printer-margin-bottom</Name>
            <Value>10</Value>
        </Property>
        <Property>
            <Name>pdf-printer-margin-left</Name>
            <Value>10</Value>
        </Property>
        <Property>
            <Name>pdf-printer-margin-right</Name>
            <Value>10</Value>
        </Property>
        <Property>
            <Name>pdf-printer-page-orientation</Name>
            <Value>landscape</Value>
        </Property>
        <Property>
            <Name>pdf-printer-show-pages</Name>
            <Value>false</Value>
        </Property>
        <Property>
            <Name>pdf-printer-include-footer</Name>
            <Value>true</Value>
        </Property>
        <Property>
            <Name>reference-notation</Name>
            <Value>crows-foot</Value>
        </Property>
        <Property>
            <Name>pages-line-color</Name>
            <Value>#CC0000</Value>
        </Property>
        <Property>
            <Name>show-grid</Name>
            <Value>false</Value>
        </Property>
        <Property>
            <Name>grid-color</Name>
            <Value>#D9D9D9</Value>
        </Property>
        <Property>
            <Name>grid-style</Name>
            <Value>solid</Value>
        </Property>
        <Property>
            <Name>grid-spacing</Name>
            <Value>2</Value>
        </Property>
        <Property>
            <Name>grid-spacing-units</Name>
            <Value>cm</Value>
        </Property>
        <Property>
            <Name>grid-subdivisions</Name>
            <Value>1</Value>
        </Property>
    </Properties>
    <DefaultAdditionalProperties>
        <Types>
            <Name>table</Name>
            <Properties/>
        </Types>
        <Types>
            <Name>column</Name>
            <Properties/>
        </Types>
        <Types>
            <Name>alternate_key</Name>
            <Properties/>
        </Types>
        <Types>
            <Name>index</Name>
            <Properties/>
        </Types>
        <Types>
            <Name>table_check</Name>
            <Properties/>
        </Types>
        <Types>
            <Name>trigger</Name>
            <Properties/>
        </Types>
        <Types>
            <Name>reference</Name>
            <Properties/>
        </Types>
        <Types>
            <Name>view</Name>
            <Properties/>
        </Types>
        <Types>
            <Name>sequence</Name>
            <Properties/>
        </Types>
        <Types>
            <Name>procedure</Name>
            <Properties/>
        </Types>
        <Types>
            <Name>all</Name>
            <Properties/>
        </Types>
        <Types>
            <Name>view_column</Name>
            <Properties/>
        </Types>
        <Types>
            <Name>primary_key</Name>
            <Properties/>
        </Types>
    </DefaultAdditionalProperties>
</DatabaseModel>
